aspen_pyconnect/__init__.py
aspen_pyconnect/aspen.py
aspen_pyconnect/utils.py
aspen_pyconnect-0.1.11.dist-info/METADATA
aspen_pyconnect-0.1.11.dist-info/WHEEL
aspen_pyconnect-0.1.11.dist-info/top_level.txt
aspen_pyconnect-0.1.11.dist-info/RECORD
