Metadata-Version: 2.1
Name: aspen-pyconnect
Version: 0.1.11
Summary: A wrapper for accessing data from Aspen IP.21.
Home-page: https://github.com/RobertLeePrice
Author: Robert Price, Jose Roberts, Arpan Seth
Author-email: rlprice410@gmail.com
License: MIT
Platform: UNKNOWN
Requires-Dist: requests
Requires-Dist: zeep
Requires-Dist: pandas
